LICENSE
dataray/__init__.py
dataray/_version.py
dataray/dataray.py
dataray/helper/__init__.py
dataray/helper/helper_func.py
dataray/tests/__init__.py
dataray/tests/test_helper_func.py
dataray-0.1.1.dist-info/LICENSE
dataray-0.1.1.dist-info/WHEEL
dataray-0.1.1.dist-info/METADATA
dataray-0.1.1.dist-info/RECORD
