Metadata-Version: 2.1
Name: dataray
Version: 0.1.1
Summary: a class of decorators helping inspect data
Home-page: https://github.com/Zhen404/dataray
License: MIT
Keywords: json,data,inspection
Author: Zhen404
Author-email: zl2632@columbia.edu
Requires-Python: >=3.7,<4.0
Classifier: License :: OSI Approved :: MIT License
Classifier: Operating System :: OS Independent
Classifier: Programming Language :: Python :: 3
Classifier: Programming Language :: Python :: 3.7
Classifier: Programming Language :: Python :: 3.8
Classifier: Topic :: Software Development :: Libraries :: Python Modules
Project-URL: Repository, https://github.com/Zhen404/dataray
